{
  "stateId": "010-kubernetes-runtime",
  "stateTitle": "Kubernetes Runtime on C2",
  "stateStatus": "implemented",
  "featurePack": "specs/010-kubernetes-runtime",
  "previousStates": ["009-order-management-matcher"],
  "nextStates": ["011-tilt-kubernetes-dev-loop"],
  "isConvergenceState": false,
  "convergenceLevel": "none",
  "lineageRole": "canonical",
  "dottedParents": [],
  "previousConvergenceState": "009-order-management-matcher",
  "nextConvergenceState": "012-platform-convergence-c3",
  "sourceBranch": "main",
  "sourceCommit": "f0056d6753b9a76295ce40ede1f32c30bd2c5f27",
  "generatedAtUtc": "2026-06-21T11:19:29Z",
  "generationEntryPoint": "bash pipeline/generate-state.sh 010-kubernetes-runtime",
  "publishTagHint": "generated/010-kubernetes-runtime/v1"
}
